README.md
setup.py
i3lockcomics/__init__.py
i3lockcomics/__main__.py
i3lockcomics/__version__.py
i3lockcomics/_args.py
i3lockcomics/_check_network.py
i3lockcomics/_getcomics.py
i3lockcomics/_printv.py
i3lockcomics/_screen.py
i3lockcomics/_timing.py
i3lockcomics/xkcd.png
i3lockcomics.egg-info/PKG-INFO
i3lockcomics.egg-info/SOURCES.txt
i3lockcomics.egg-info/dependency_links.txt
i3lockcomics.egg-info/entry_points.txt
i3lockcomics.egg-info/requires.txt
i3lockcomics.egg-info/top_level.txt
i3lockcomics/fonts/OpenSans-Italic.ttf