Metadata-Version: 2.1
Name: i3lockcomics
Version: 1.0.9
Summary: Gets the newest edition of a comic strip and use it in i3lock
Home-page: https://github.com/armandg/i3lockcomics
Author: armandg
Author-email: armandg@gmail.com
License: GPL-v3.0
Platform: UNKNOWN
